doc2anki/__init__.py
doc2anki/__main__.py
doc2anki/cli.py
doc2anki/py.typed
doc2anki/config/__init__.py
doc2anki/config/loader.py
doc2anki/config/models.py
doc2anki/llm/__init__.py
doc2anki/llm/client.py
doc2anki/llm/extractor.py
doc2anki/llm/prompt.py
doc2anki/models/__init__.py
doc2anki/models/cards.py
doc2anki/output/__init__.py
doc2anki/output/apkg.py
doc2anki/parser/__init__.py
doc2anki/parser/builder.py
doc2anki/parser/chunker.py
doc2anki/parser/markdown.py
doc2anki/parser/metadata.py
doc2anki/parser/orgmode.py
doc2anki/parser/tree.py
doc2anki/pipeline/__init__.py
doc2anki/pipeline/classifier.py
doc2anki/pipeline/context.py
doc2anki/pipeline/interactive.py
doc2anki/pipeline/processor.py
doc2anki/templates/__init__.py
doc2anki/templates/generate_cards.j2
doc2anki-0.2.0.dist-info/METADATA
doc2anki-0.2.0.dist-info/WHEEL
doc2anki-0.2.0.dist-info/entry_points.txt
doc2anki-0.2.0.dist-info/licenses/LICENSE
doc2anki-0.2.0.dist-info/RECORD
