Metadata-Version: 2.4
Name: doc2anki
Version: 0.2.0
Summary: Convert knowledge base documents to Anki flashcards
Author-email: SOV710 <chris916911179@outlook.com>
License-File: LICENSE
Requires-Python: >=3.12
Requires-Dist: genanki>=0.13.0
Requires-Dist: jinja2>=3.0.0
Requires-Dist: openai>=1.0.0
Requires-Dist: orgparse>=0.4.0
Requires-Dist: pydantic>=2.0.0
Requires-Dist: python-dotenv>=1.0.0
Requires-Dist: pyyaml>=6.0.0
Requires-Dist: rich>=13.0.0
Requires-Dist: tiktoken>=0.5.0
Requires-Dist: tomli>=2.0.0
Requires-Dist: tree-sitter-markdown>=0.3.0
Requires-Dist: tree-sitter>=0.24.0
Requires-Dist: typer>=0.9.0
